stackconfig/__init__.py
stackconfig/cli.py
stackconfig/stackconfig.py
stackconfig/utils/__init__.py
stackconfig/utils/jinja2_utils.py
stackconfig/utils/validate_compose.py
stackconfig/utils/yaml_utils.py
stackconfig-1.0.2.dist-info/LICENSE.md
stackconfig-1.0.2.dist-info/METADATA
stackconfig-1.0.2.dist-info/WHEEL
stackconfig-1.0.2.dist-info/entry_points.txt
stackconfig-1.0.2.dist-info/top_level.txt
stackconfig-1.0.2.dist-info/RECORD
