Metadata-Version: 2.1
Name: stackconfig
Version: 1.0.2
Summary: Render, merge and validate docker_compose files for deploying a stack
Home-page: https://github.com/Sciencelogic/stackconfig
Download-URL: https://github.com/Sciencelogic/stackconfig/tarball/
Author: Sciencelogic
License: BSD
Keywords: stackconfig,docker-compose-config,compose-jinja2,docker-compose-jinja2
Classifier: Development Status :: 3 - Alpha
Classifier: Intended Audience :: Developers
Classifier: Programming Language :: Python :: 3
License-File: LICENSE.md
Requires-Dist: Click
Requires-Dist: docker-compose<=1.29.2,>=1.26.2
Requires-Dist: pyyaml>=5.4.1
Requires-Dist: MarkupSafe
Requires-Dist: jinja2
